environment_tools/__init__.py
environment_tools/config.py
environment_tools/type_utils.py
environment_tools-1.1.3.dist-info/DESCRIPTION.rst
environment_tools-1.1.3.dist-info/METADATA
environment_tools-1.1.3.dist-info/RECORD
environment_tools-1.1.3.dist-info/WHEEL
environment_tools-1.1.3.dist-info/metadata.json
environment_tools-1.1.3.dist-info/top_level.txt
