Metadata-Version: 2.0
Name: environment-tools
Version: 1.1.3
Summary: Utilities for working with hierarchical environments
Home-page: UNKNOWN
Author: UNKNOWN
Author-email: UNKNOWN
License: Copyright Yelp 2015, All Rights Reserved
Platform: UNKNOWN
Requires-Dist: networkx (>=1.9.1)
